pythonExample/__init__.py
pythonExample/pythonProj.py
jfrog_python_example-5.0.dist-info/METADATA
jfrog_python_example-5.0.dist-info/WHEEL
jfrog_python_example-5.0.dist-info/top_level.txt
jfrog_python_example-5.0.dist-info/RECORD
