Metadata-Version: 2.4
Name: jfrog-python-example
Version: 5.0
Summary: Project example for building Python project with JFrog products
Home-page: https://github.com/jfrog/project-examples
Author: JFrog
Author-email: jfrog@jfrog.com
Requires-Python: >=3.13
Requires-Dist: PyYAML>3.11
Requires-Dist: nltk
Dynamic: author
Dynamic: author-email
Dynamic: home-page
Dynamic: requires-dist
Dynamic: requires-python
Dynamic: summary
